BianchengXiaobaiDeDiyibenPythonRumenShu/README.md
BianchengXiaobaiDeDiyibenPythonRumenShu/__init__.py
BianchengXiaobaiDeDiyibenPythonRumenShu/__main__.py
BianchengXiaobaiDeDiyibenPythonRumenShu/file.epub
BianchengXiaobaiDeDiyibenPythonRumenShu/index.html
BianchengXiaobaiDeDiyibenPythonRumenShu/css/__init__.py
BianchengXiaobaiDeDiyibenPythonRumenShu/css/annotations.css
BianchengXiaobaiDeDiyibenPythonRumenShu/css/main.css
BianchengXiaobaiDeDiyibenPythonRumenShu/css/normalize.css
BianchengXiaobaiDeDiyibenPythonRumenShu/css/popup.css
BianchengXiaobaiDeDiyibenPythonRumenShu/font/__init__.py
BianchengXiaobaiDeDiyibenPythonRumenShu/font/fontello.eot
BianchengXiaobaiDeDiyibenPythonRumenShu/font/fontello.svg
BianchengXiaobaiDeDiyibenPythonRumenShu/font/fontello.ttf
BianchengXiaobaiDeDiyibenPythonRumenShu/font/fontello.woff
BianchengXiaobaiDeDiyibenPythonRumenShu/img/__init__.py
BianchengXiaobaiDeDiyibenPythonRumenShu/img/annotator-glyph-sprite.png
BianchengXiaobaiDeDiyibenPythonRumenShu/img/annotator-icon-sprite.png
BianchengXiaobaiDeDiyibenPythonRumenShu/img/apple-touch-icon.png
BianchengXiaobaiDeDiyibenPythonRumenShu/img/cancelfullscreen.png
BianchengXiaobaiDeDiyibenPythonRumenShu/img/close.png
BianchengXiaobaiDeDiyibenPythonRumenShu/img/fullscreen.png
BianchengXiaobaiDeDiyibenPythonRumenShu/img/loader.gif
BianchengXiaobaiDeDiyibenPythonRumenShu/img/menu-icon.png
BianchengXiaobaiDeDiyibenPythonRumenShu/img/save.png
BianchengXiaobaiDeDiyibenPythonRumenShu/img/saved.png
BianchengXiaobaiDeDiyibenPythonRumenShu/img/settings-s.png
BianchengXiaobaiDeDiyibenPythonRumenShu/img/settings.png
BianchengXiaobaiDeDiyibenPythonRumenShu/img/star.png
BianchengXiaobaiDeDiyibenPythonRumenShu/js/__init__.py
BianchengXiaobaiDeDiyibenPythonRumenShu/js/epub.js
BianchengXiaobaiDeDiyibenPythonRumenShu/js/epub.min.js
BianchengXiaobaiDeDiyibenPythonRumenShu/js/epub.min.map
BianchengXiaobaiDeDiyibenPythonRumenShu/js/hooks.min.js
BianchengXiaobaiDeDiyibenPythonRumenShu/js/hooks.min.map
biancheng_xiaobai_de_diyiben_python_rumen_shu-2024.3.1.0.dist-info/METADATA
biancheng_xiaobai_de_diyiben_python_rumen_shu-2024.3.1.0.dist-info/WHEEL
biancheng_xiaobai_de_diyiben_python_rumen_shu-2024.3.1.0.dist-info/entry_points.txt
biancheng_xiaobai_de_diyiben_python_rumen_shu-2024.3.1.0.dist-info/top_level.txt
biancheng_xiaobai_de_diyiben_python_rumen_shu-2024.3.1.0.dist-info/RECORD
